<?xml version="1.0" encoding="UTF-8"?>
<persistence version="2.1" xmlns="http://xmlns.jcp.org/xml/ns/persistence" xmlns:xsi="http://www.w3.org/2001/XMLSchema-instance" xsi:schemaLocation="http://xmlns.jcp.org/xml/ns/persistence http://xmlns.jcp.org/xml/ns/persistence/persistence_2_1.xsd">
	<persistence-unit name="jpa">
		<class>com.nixmash.springdata.jpa.model.Post</class>
		<properties>
			<property name="toplink.jdbc.url" value="jdbc:mysql://localhost:3306/dev_nixmashspring"/>
			<property name="toplink.jdbc.driver" value="com.mysql.jdbc.Driver"/>
			<property name="toplink.jdbc.user"/>
			<property name="toplink.jdbc.password"/>
			<property name="hibernate.connection.url" value="jdbc:mysql://localhost:3306/dev_nixmashspring"/>
			<property name="hibernate.connection.driver_class" value="com.mysql.jdbc.Driver"/>
			<property name="hibernate.connection.username"/>
			<property name="hibernate.connection.password"/>
			<property name="openjpa.ConnectionURL" value="jdbc:mysql://localhost:3306/dev_nixmashspring"/>
			<property name="openjpa.ConnectionDriverName" value="com.mysql.jdbc.Driver"/>
			<property name="openjpa.ConnectionUserName"/>
			<property name="openjpa.ConnectionPassword"/>
			<property name="eclipselink.jdbc.url" value="jdbc:mysql://localhost:3306/dev_nixmashspring"/>
			<property name="eclipselink.jdbc.driver" value="com.mysql.jdbc.Driver"/>
			<property name="eclipselink.jdbc.user"/>
			<property name="eclipselink.jdbc.password"/>
		</properties>
	</persistence-unit>
</persistence>
